sendenv/__init__.py
sendenv/cli.py
sendenv/config.py
sendenv/main.py
sendenv/vault.py
sendenv/vault_manager.py
sendenv-0.1.14.dist-info/LICENSE
sendenv-0.1.14.dist-info/METADATA
sendenv-0.1.14.dist-info/WHEEL
sendenv-0.1.14.dist-info/entry_points.txt
sendenv-0.1.14.dist-info/top_level.txt
sendenv-0.1.14.dist-info/RECORD
